{
  "8732923778f83df576e551800c5f68d9": {
    "temperature": 85.64,
    "temp": 85.64,
    "windSpeed": 51.225926,
    "windDirectionDeg": 193,
    "windOut": false,
    "windIn": false,
    "windDir": "neutral",
    "forecastTimeUtc": "2026-05-17T17:00",
    "humidityPct": 52,
    "precipitationMm": 0,
    "_meta": {
      "homeTeam": "Colorado Rockies",
      "geocode": {
        "lat": 32.38817,
        "lon": -100.86456,
        "nameUsed": "Colorado"
      },
      "ingestedAt": "2026-05-17T20:25:40.578Z"
    }
  },
  "4a7ed5c0f59bf539dffd13712f0d22e3": {
    "temperature": 53.42,
    "temp": 53.42,
    "windSpeed": 3.5791040000000005,
    "windDirectionDeg": 297,
    "windOut": false,
    "windIn": false,
    "windDir": "neutral",
    "forecastTimeUtc": "2026-05-17T19:00",
    "humidityPct": 75,
    "precipitationMm": 0,
    "_meta": {
      "homeTeam": "Seattle Mariners",
      "geocode": {
        "lat": 47.60621,
        "lon": -122.33207,
        "nameUsed": "Seattle"
      },
      "ingestedAt": "2026-05-17T20:25:40.578Z"
    }
  }
}