{
  "slade cecconi": {
    "playerId": 677944,
    "fullName": "Slade Cecconi",
    "throws": null,
    "teamId": 114,
    "teamName": "Cleveland Guardians",
    "season": "2026",
    "gamesPitched": 9,
    "gamesStarted": 9,
    "inningsPitched": 43.2,
    "battersFaced": 200,
    "strikeOuts": 35,
    "walks": 16,
    "hits": 54,
    "earnedRuns": 28,
    "homeRunsAllowed": 8,
    "pitchCount": null,
    "kRate": 0.175,
    "bbRate": 0.08,
    "k9": 7.29,
    "whip": 1.62,
    "era": 5.77,
    "recentPitches": null,
    "restDays": null,
    "velocityMph": null,
    "source": "mlb_statsapi_season",
    "ingestedAt": "2026-05-12T22:56:04.837Z"
  },
  "walbert urena": {
    "playerId": 700712,
    "fullName": "Walbert Ureña",
    "throws": null,
    "teamId": 108,
    "teamName": "Los Angeles Angels",
    "season": "2026",
    "gamesPitched": 7,
    "gamesStarted": 5,
    "inningsPitched": 24.1,
    "battersFaced": 107,
    "strikeOuts": 25,
    "walks": 16,
    "hits": 20,
    "earnedRuns": 8,
    "homeRunsAllowed": 1,
    "pitchCount": null,
    "kRate": 0.2336,
    "bbRate": 0.1495,
    "k9": 9.34,
    "whip": 1.49,
    "era": 2.96,
    "recentPitches": null,
    "restDays": null,
    "velocityMph": null,
    "source": "mlb_statsapi_season",
    "ingestedAt": "2026-05-12T22:56:04.837Z"
  },
  "trevor rogers": {
    "playerId": 669432,
    "fullName": "Trevor Rogers",
    "throws": null,
    "teamId": 110,
    "teamName": "Baltimore Orioles",
    "season": "2026",
    "gamesPitched": 7,
    "gamesStarted": 7,
    "inningsPitched": 32.1,
    "battersFaced": 141,
    "strikeOuts": 29,
    "walks": 10,
    "hits": 36,
    "earnedRuns": 17,
    "homeRunsAllowed": 4,
    "pitchCount": null,
    "kRate": 0.2057,
    "bbRate": 0.0709,
    "k9": 8.13,
    "whip": 1.43,
    "era": 4.73,
    "recentPitches": null,
    "restDays": null,
    "velocityMph": null,
    "source": "mlb_statsapi_season",
    "ingestedAt": "2026-05-12T22:56:04.837Z"
  },
  "will warren": {
    "playerId": 701542,
    "fullName": "Will Warren",
    "throws": null,
    "teamId": 147,
    "teamName": "New York Yankees",
    "season": "2026",
    "gamesPitched": 9,
    "gamesStarted": 9,
    "inningsPitched": 42.2,
    "battersFaced": 177,
    "strikeOuts": 54,
    "walks": 11,
    "hits": 39,
    "earnedRuns": 16,
    "homeRunsAllowed": 6,
    "pitchCount": null,
    "kRate": 0.3051,
    "bbRate": 0.0621,
    "k9": 11.52,
    "whip": 1.18,
    "era": 3.38,
    "recentPitches": null,
    "restDays": null,
    "velocityMph": null,
    "source": "mlb_statsapi_season",
    "ingestedAt": "2026-05-12T22:56:04.837Z"
  },
  "brady singer": {
    "playerId": 663903,
    "fullName": "Brady Singer",
    "throws": null,
    "teamId": 113,
    "teamName": "Cincinnati Reds",
    "season": "2026",
    "gamesPitched": 9,
    "gamesStarted": 9,
    "inningsPitched": 39.1,
    "battersFaced": 181,
    "strikeOuts": 28,
    "walks": 10,
    "hits": 53,
    "earnedRuns": 24,
    "homeRunsAllowed": 8,
    "pitchCount": null,
    "kRate": 0.1547,
    "bbRate": 0.0552,
    "k9": 6.45,
    "whip": 1.61,
    "era": 5.49,
    "recentPitches": null,
    "restDays": null,
    "velocityMph": null,
    "source": "mlb_statsapi_season",
    "ingestedAt": "2026-05-12T22:56:04.838Z"
  },
  "miles mikolas": {
    "playerId": 571945,
    "fullName": "Miles Mikolas",
    "throws": null,
    "teamId": 120,
    "teamName": "Washington Nationals",
    "season": "2026",
    "gamesPitched": 9,
    "gamesStarted": 6,
    "inningsPitched": 33.2,
    "battersFaced": 149,
    "strikeOuts": 22,
    "walks": 11,
    "hits": 39,
    "earnedRuns": 27,
    "homeRunsAllowed": 9,
    "pitchCount": null,
    "kRate": 0.1477,
    "bbRate": 0.0738,
    "k9": 5.96,
    "whip": 1.51,
    "era": 7.22,
    "recentPitches": null,
    "restDays": null,
    "velocityMph": null,
    "source": "mlb_statsapi_season",
    "ingestedAt": "2026-05-12T22:56:04.838Z"
  },
  "paul skenes": {
    "playerId": 694973,
    "fullName": "Paul Skenes",
    "throws": null,
    "teamId": 134,
    "teamName": "Pittsburgh Pirates",
    "season": "2026",
    "gamesPitched": 9,
    "gamesStarted": 9,
    "inningsPitched": 43,
    "battersFaced": 162,
    "strikeOuts": 49,
    "walks": 7,
    "hits": 23,
    "earnedRuns": 11,
    "homeRunsAllowed": 4,
    "pitchCount": null,
    "kRate": 0.3025,
    "bbRate": 0.0432,
    "k9": 10.26,
    "whip": 0.7,
    "era": 2.3,
    "recentPitches": null,
    "restDays": null,
    "velocityMph": null,
    "source": "mlb_statsapi_season",
    "ingestedAt": "2026-05-12T22:56:04.838Z"
  },
  "michael lorenzen": {
    "playerId": 547179,
    "fullName": "Michael Lorenzen",
    "throws": null,
    "teamId": 115,
    "teamName": "Colorado Rockies",
    "season": "2026",
    "gamesPitched": 10,
    "gamesStarted": 9,
    "inningsPitched": 39.1,
    "battersFaced": 193,
    "strikeOuts": 27,
    "walks": 13,
    "hits": 63,
    "earnedRuns": 30,
    "homeRunsAllowed": 7,
    "pitchCount": null,
    "kRate": 0.1399,
    "bbRate": 0.0674,
    "k9": 6.21,
    "whip": 1.94,
    "era": 6.86,
    "recentPitches": null,
    "restDays": null,
    "velocityMph": null,
    "source": "mlb_statsapi_season",
    "ingestedAt": "2026-05-12T22:56:04.838Z"
  },
  "jovani moran": {
    "playerId": 663558,
    "fullName": "Jovani Morán",
    "throws": null,
    "teamId": 111,
    "teamName": "Boston Red Sox",
    "season": "2026",
    "gamesPitched": 13,
    "gamesStarted": 2,
    "inningsPitched": 22.2,
    "battersFaced": 95,
    "strikeOuts": 22,
    "walks": 14,
    "hits": 14,
    "earnedRuns": 8,
    "homeRunsAllowed": 4,
    "pitchCount": null,
    "kRate": 0.2316,
    "bbRate": 0.1474,
    "k9": 8.92,
    "whip": 1.26,
    "era": 3.18,
    "recentPitches": null,
    "restDays": null,
    "velocityMph": null,
    "source": "mlb_statsapi_season",
    "ingestedAt": "2026-05-12T22:56:04.838Z"
  },
  "zack wheeler": {
    "playerId": 554430,
    "fullName": "Zack Wheeler",
    "throws": null,
    "teamId": 143,
    "teamName": "Philadelphia Phillies",
    "season": "2026",
    "gamesPitched": 3,
    "gamesStarted": 3,
    "inningsPitched": 17.1,
    "battersFaced": 68,
    "strikeOuts": 18,
    "walks": 6,
    "hits": 11,
    "earnedRuns": 6,
    "homeRunsAllowed": 1,
    "pitchCount": null,
    "kRate": 0.2647,
    "bbRate": 0.0882,
    "k9": 9.47,
    "whip": 0.99,
    "era": 3.12,
    "recentPitches": null,
    "restDays": null,
    "velocityMph": null,
    "source": "mlb_statsapi_season",
    "ingestedAt": "2026-05-12T22:56:04.838Z"
  },
  "patrick corbin": {
    "playerId": 571578,
    "fullName": "Patrick Corbin",
    "throws": null,
    "teamId": 141,
    "teamName": "Toronto Blue Jays",
    "season": "2026",
    "gamesPitched": 6,
    "gamesStarted": 6,
    "inningsPitched": 30,
    "battersFaced": 124,
    "strikeOuts": 21,
    "walks": 9,
    "hits": 29,
    "earnedRuns": 12,
    "homeRunsAllowed": 3,
    "pitchCount": null,
    "kRate": 0.1694,
    "bbRate": 0.0726,
    "k9": 6.3,
    "whip": 1.27,
    "era": 3.6,
    "recentPitches": null,
    "restDays": null,
    "velocityMph": null,
    "source": "mlb_statsapi_season",
    "ingestedAt": "2026-05-12T22:56:04.838Z"
  },
  "shane mcclanahan": {
    "playerId": 663556,
    "fullName": "Shane McClanahan",
    "throws": null,
    "teamId": 139,
    "teamName": "Tampa Bay Rays",
    "season": "2026",
    "gamesPitched": 7,
    "gamesStarted": 7,
    "inningsPitched": 34.2,
    "battersFaced": 141,
    "strikeOuts": 34,
    "walks": 14,
    "hits": 23,
    "earnedRuns": 10,
    "homeRunsAllowed": 1,
    "pitchCount": null,
    "kRate": 0.2411,
    "bbRate": 0.0993,
    "k9": 8.95,
    "whip": 1.08,
    "era": 2.6,
    "recentPitches": null,
    "restDays": null,
    "velocityMph": null,
    "source": "mlb_statsapi_season",
    "ingestedAt": "2026-05-12T22:56:04.838Z"
  },
  "freddy peralta": {
    "playerId": 642547,
    "fullName": "Freddy Peralta",
    "throws": null,
    "teamId": 121,
    "teamName": "New York Mets",
    "season": "2026",
    "gamesPitched": 8,
    "gamesStarted": 8,
    "inningsPitched": 43.1,
    "battersFaced": 185,
    "strikeOuts": 43,
    "walks": 18,
    "hits": 34,
    "earnedRuns": 15,
    "homeRunsAllowed": 4,
    "pitchCount": null,
    "kRate": 0.2324,
    "bbRate": 0.0973,
    "k9": 8.98,
    "whip": 1.21,
    "era": 3.12,
    "recentPitches": null,
    "restDays": null,
    "velocityMph": null,
    "source": "mlb_statsapi_season",
    "ingestedAt": "2026-05-12T22:56:04.838Z"
  },
  "jack flaherty": {
    "playerId": 656427,
    "fullName": "Jack Flaherty",
    "throws": null,
    "teamId": 116,
    "teamName": "Detroit Tigers",
    "season": "2026",
    "gamesPitched": 8,
    "gamesStarted": 8,
    "inningsPitched": 34,
    "battersFaced": 162,
    "strikeOuts": 42,
    "walks": 26,
    "hits": 30,
    "earnedRuns": 21,
    "homeRunsAllowed": 5,
    "pitchCount": null,
    "kRate": 0.2593,
    "bbRate": 0.1605,
    "k9": 11.12,
    "whip": 1.65,
    "era": 5.56,
    "recentPitches": null,
    "restDays": null,
    "velocityMph": null,
    "source": "mlb_statsapi_season",
    "ingestedAt": "2026-05-12T22:56:04.838Z"
  },
  "grant holmes": {
    "playerId": 656550,
    "fullName": "Grant Holmes",
    "throws": null,
    "teamId": 144,
    "teamName": "Atlanta Braves",
    "season": "2026",
    "gamesPitched": 7,
    "gamesStarted": 7,
    "inningsPitched": 37.1,
    "battersFaced": 160,
    "strikeOuts": 29,
    "walks": 17,
    "hits": 32,
    "earnedRuns": 18,
    "homeRunsAllowed": 6,
    "pitchCount": null,
    "kRate": 0.1812,
    "bbRate": 0.1062,
    "k9": 7.04,
    "whip": 1.32,
    "era": 4.34,
    "recentPitches": null,
    "restDays": null,
    "velocityMph": null,
    "source": "mlb_statsapi_season",
    "ingestedAt": "2026-05-12T22:56:04.838Z"
  },
  "colin rea": {
    "playerId": 607067,
    "fullName": "Colin Rea",
    "throws": null,
    "teamId": 112,
    "teamName": "Chicago Cubs",
    "season": "2026",
    "gamesPitched": 8,
    "gamesStarted": 5,
    "inningsPitched": 38,
    "battersFaced": 166,
    "strikeOuts": 35,
    "walks": 12,
    "hits": 40,
    "earnedRuns": 17,
    "homeRunsAllowed": 4,
    "pitchCount": null,
    "kRate": 0.2108,
    "bbRate": 0.0723,
    "k9": 8.29,
    "whip": 1.37,
    "era": 4.03,
    "recentPitches": null,
    "restDays": null,
    "velocityMph": null,
    "source": "mlb_statsapi_season",
    "ingestedAt": "2026-05-12T22:56:04.838Z"
  },
  "erick fedde": {
    "playerId": 607200,
    "fullName": "Erick Fedde",
    "throws": null,
    "teamId": 145,
    "teamName": "Chicago White Sox",
    "season": "2026",
    "gamesPitched": 7,
    "gamesStarted": 5,
    "inningsPitched": 38,
    "battersFaced": 155,
    "strikeOuts": 24,
    "walks": 13,
    "hits": 30,
    "earnedRuns": 16,
    "homeRunsAllowed": 8,
    "pitchCount": null,
    "kRate": 0.1548,
    "bbRate": 0.0839,
    "k9": 5.68,
    "whip": 1.13,
    "era": 3.79,
    "recentPitches": null,
    "restDays": null,
    "velocityMph": null,
    "source": "mlb_statsapi_season",
    "ingestedAt": "2026-05-12T22:56:04.838Z"
  },
  "stephen kolek": {
    "playerId": 663568,
    "fullName": "Stephen Kolek",
    "throws": null,
    "teamId": 118,
    "teamName": "Kansas City Royals",
    "season": "2026",
    "gamesPitched": 1,
    "gamesStarted": 1,
    "inningsPitched": 6,
    "battersFaced": 22,
    "strikeOuts": 3,
    "walks": 0,
    "hits": 4,
    "earnedRuns": 3,
    "homeRunsAllowed": 1,
    "pitchCount": null,
    "kRate": 0.1364,
    "bbRate": 0,
    "k9": 4.5,
    "whip": 0.67,
    "era": 4.5,
    "recentPitches": null,
    "restDays": null,
    "velocityMph": null,
    "source": "mlb_statsapi_season",
    "ingestedAt": "2026-05-12T22:56:04.838Z"
  },
  "bailey ober": {
    "playerId": 641927,
    "fullName": "Bailey Ober",
    "throws": null,
    "teamId": 142,
    "teamName": "Minnesota Twins",
    "season": "2026",
    "gamesPitched": 8,
    "gamesStarted": 8,
    "inningsPitched": 43,
    "battersFaced": 180,
    "strikeOuts": 32,
    "walks": 15,
    "hits": 36,
    "earnedRuns": 20,
    "homeRunsAllowed": 5,
    "pitchCount": null,
    "kRate": 0.1778,
    "bbRate": 0.0833,
    "k9": 6.7,
    "whip": 1.19,
    "era": 4.19,
    "recentPitches": null,
    "restDays": null,
    "velocityMph": null,
    "source": "mlb_statsapi_season",
    "ingestedAt": "2026-05-12T22:56:04.838Z"
  },
  "eury perez": {
    "playerId": 691587,
    "fullName": "Eury Pérez",
    "throws": null,
    "teamId": 146,
    "teamName": "Miami Marlins",
    "season": "2026",
    "gamesPitched": 8,
    "gamesStarted": 8,
    "inningsPitched": 41.1,
    "battersFaced": 182,
    "strikeOuts": 45,
    "walks": 21,
    "hits": 38,
    "earnedRuns": 23,
    "homeRunsAllowed": 7,
    "pitchCount": null,
    "kRate": 0.2473,
    "bbRate": 0.1154,
    "k9": 9.85,
    "whip": 1.44,
    "era": 5.01,
    "recentPitches": null,
    "restDays": null,
    "velocityMph": null,
    "source": "mlb_statsapi_season",
    "ingestedAt": "2026-05-12T22:56:04.838Z"
  },
  "brandon sproat": {
    "playerId": 687075,
    "fullName": "Brandon Sproat",
    "throws": null,
    "teamId": 158,
    "teamName": "Milwaukee Brewers",
    "season": "2026",
    "gamesPitched": 7,
    "gamesStarted": 5,
    "inningsPitched": 30.2,
    "battersFaced": 131,
    "strikeOuts": 30,
    "walks": 18,
    "hits": 29,
    "earnedRuns": 20,
    "homeRunsAllowed": 7,
    "pitchCount": null,
    "kRate": 0.229,
    "bbRate": 0.1374,
    "k9": 8.94,
    "whip": 1.56,
    "era": 5.87,
    "recentPitches": null,
    "restDays": null,
    "velocityMph": null,
    "source": "mlb_statsapi_season",
    "ingestedAt": "2026-05-12T22:56:04.838Z"
  },
  "bradgley rodriguez": {
    "playerId": 699134,
    "fullName": "Bradgley Rodriguez",
    "throws": null,
    "teamId": 135,
    "teamName": "San Diego Padres",
    "season": "2026",
    "gamesPitched": 17,
    "gamesStarted": 1,
    "inningsPitched": 19.2,
    "battersFaced": 78,
    "strikeOuts": 14,
    "walks": 5,
    "hits": 15,
    "earnedRuns": 4,
    "homeRunsAllowed": 0,
    "pitchCount": null,
    "kRate": 0.1795,
    "bbRate": 0.0641,
    "k9": 6.56,
    "whip": 1.04,
    "era": 1.83,
    "recentPitches": null,
    "restDays": null,
    "velocityMph": null,
    "source": "mlb_statsapi_season",
    "ingestedAt": "2026-05-12T22:56:04.838Z"
  },
  "mackenzie gore": {
    "playerId": 669022,
    "fullName": "MacKenzie Gore",
    "throws": null,
    "teamId": 140,
    "teamName": "Texas Rangers",
    "season": "2026",
    "gamesPitched": 8,
    "gamesStarted": 8,
    "inningsPitched": 40,
    "battersFaced": 176,
    "strikeOuts": 48,
    "walks": 21,
    "hits": 35,
    "earnedRuns": 23,
    "homeRunsAllowed": 5,
    "pitchCount": null,
    "kRate": 0.2727,
    "bbRate": 0.1193,
    "k9": 10.8,
    "whip": 1.4,
    "era": 5.18,
    "recentPitches": null,
    "restDays": null,
    "velocityMph": null,
    "source": "mlb_statsapi_season",
    "ingestedAt": "2026-05-12T22:56:04.838Z"
  },
  "zac gallen": {
    "playerId": 668678,
    "fullName": "Zac Gallen",
    "throws": null,
    "teamId": 109,
    "teamName": "Arizona Diamondbacks",
    "season": "2026",
    "gamesPitched": 8,
    "gamesStarted": 8,
    "inningsPitched": 38.1,
    "battersFaced": 169,
    "strikeOuts": 25,
    "walks": 12,
    "hits": 45,
    "earnedRuns": 20,
    "homeRunsAllowed": 4,
    "pitchCount": null,
    "kRate": 0.1479,
    "bbRate": 0.071,
    "k9": 5.91,
    "whip": 1.5,
    "era": 4.7,
    "recentPitches": null,
    "restDays": null,
    "velocityMph": null,
    "source": "mlb_statsapi_season",
    "ingestedAt": "2026-05-12T22:56:04.838Z"
  },
  "tatsuya imai": {
    "playerId": 837227,
    "fullName": "Tatsuya Imai",
    "throws": null,
    "teamId": 117,
    "teamName": "Houston Astros",
    "season": "2026",
    "gamesPitched": 3,
    "gamesStarted": 3,
    "inningsPitched": 8.2,
    "battersFaced": 44,
    "strikeOuts": 13,
    "walks": 11,
    "hits": 7,
    "earnedRuns": 7,
    "homeRunsAllowed": 0,
    "pitchCount": null,
    "kRate": 0.2955,
    "bbRate": 0.25,
    "k9": 14.27,
    "whip": 2.2,
    "era": 7.27,
    "recentPitches": null,
    "restDays": null,
    "velocityMph": null,
    "source": "mlb_statsapi_season",
    "ingestedAt": "2026-05-12T22:56:04.838Z"
  },
  "bryan woo": {
    "playerId": 693433,
    "fullName": "Bryan Woo",
    "throws": null,
    "teamId": 136,
    "teamName": "Seattle Mariners",
    "season": "2026",
    "gamesPitched": 8,
    "gamesStarted": 8,
    "inningsPitched": 47,
    "battersFaced": 187,
    "strikeOuts": 38,
    "walks": 8,
    "hits": 39,
    "earnedRuns": 21,
    "homeRunsAllowed": 6,
    "pitchCount": null,
    "kRate": 0.2032,
    "bbRate": 0.0428,
    "k9": 7.28,
    "whip": 1,
    "era": 4.02,
    "recentPitches": null,
    "restDays": null,
    "velocityMph": null,
    "source": "mlb_statsapi_season",
    "ingestedAt": "2026-05-12T22:56:04.838Z"
  },
  "jeffrey springs": {
    "playerId": 605488,
    "fullName": "Jeffrey Springs",
    "throws": null,
    "teamId": 133,
    "teamName": "Athletics",
    "season": "2026",
    "gamesPitched": 8,
    "gamesStarted": 8,
    "inningsPitched": 44,
    "battersFaced": 181,
    "strikeOuts": 39,
    "walks": 12,
    "hits": 38,
    "earnedRuns": 19,
    "homeRunsAllowed": 7,
    "pitchCount": null,
    "kRate": 0.2155,
    "bbRate": 0.0663,
    "k9": 7.98,
    "whip": 1.14,
    "era": 3.89,
    "recentPitches": null,
    "restDays": null,
    "velocityMph": null,
    "source": "mlb_statsapi_season",
    "ingestedAt": "2026-05-12T22:56:04.838Z"
  },
  "andre pallante": {
    "playerId": 669467,
    "fullName": "Andre Pallante",
    "throws": null,
    "teamId": 138,
    "teamName": "St. Louis Cardinals",
    "season": "2026",
    "gamesPitched": 7,
    "gamesStarted": 7,
    "inningsPitched": 37.1,
    "battersFaced": 165,
    "strikeOuts": 29,
    "walks": 16,
    "hits": 35,
    "earnedRuns": 18,
    "homeRunsAllowed": 5,
    "pitchCount": null,
    "kRate": 0.1758,
    "bbRate": 0.097,
    "k9": 7.04,
    "whip": 1.37,
    "era": 4.34,
    "recentPitches": null,
    "restDays": null,
    "velocityMph": null,
    "source": "mlb_statsapi_season",
    "ingestedAt": "2026-05-12T22:56:04.838Z"
  },
  "yoshinobu yamamoto": {
    "playerId": 808967,
    "fullName": "Yoshinobu Yamamoto",
    "throws": null,
    "teamId": 119,
    "teamName": "Los Angeles Dodgers",
    "season": "2026",
    "gamesPitched": 7,
    "gamesStarted": 7,
    "inningsPitched": 43.2,
    "battersFaced": 170,
    "strikeOuts": 40,
    "walks": 10,
    "hits": 34,
    "earnedRuns": 15,
    "homeRunsAllowed": 5,
    "pitchCount": null,
    "kRate": 0.2353,
    "bbRate": 0.0588,
    "k9": 8.33,
    "whip": 1.02,
    "era": 3.09,
    "recentPitches": null,
    "restDays": null,
    "velocityMph": null,
    "source": "mlb_statsapi_season",
    "ingestedAt": "2026-05-12T22:56:04.838Z"
  },
  "adrian houser": {
    "playerId": 605288,
    "fullName": "Adrian Houser",
    "throws": null,
    "teamId": 137,
    "teamName": "San Francisco Giants",
    "season": "2026",
    "gamesPitched": 7,
    "gamesStarted": 7,
    "inningsPitched": 36.1,
    "battersFaced": 166,
    "strikeOuts": 19,
    "walks": 11,
    "hits": 45,
    "earnedRuns": 25,
    "homeRunsAllowed": 7,
    "pitchCount": null,
    "kRate": 0.1145,
    "bbRate": 0.0663,
    "k9": 4.74,
    "whip": 1.55,
    "era": 6.19,
    "recentPitches": null,
    "restDays": null,
    "velocityMph": null,
    "source": "mlb_statsapi_season",
    "ingestedAt": "2026-05-12T22:56:04.838Z"
  }
}